CodeMonitor/__init__.py
CodeMonitor/telegram.py
CodeMonitor-1.0.2.dist-info/LICENSE
CodeMonitor-1.0.2.dist-info/METADATA
CodeMonitor-1.0.2.dist-info/WHEEL
CodeMonitor-1.0.2.dist-info/top_level.txt
CodeMonitor-1.0.2.dist-info/RECORD
